.coveragerc
.editorconfig
.gitignore
.travis.yml
LICENSE
README.md
democritus_math_docs.json
pyproject.toml
requirements.txt
requirements_dev.txt
setup.cfg
setup.py
.github/workflows/python-publish.yml
democritus_math/__init__.py
democritus_math/maths.py
democritus_math.egg-info/PKG-INFO
democritus_math.egg-info/SOURCES.txt
democritus_math.egg-info/dependency_links.txt
democritus_math.egg-info/requires.txt
democritus_math.egg-info/top_level.txt
democritus_math.egg-info/zip-safe
tests/__init__.py
tests/test_maths.py